{"note":"This file is an internal implementation detail to speed up HTML report generation. Its format can change at any time. You might be looking for the JSON report: https://coverage.rtfd.io/cmd.html#cmd-json","format":5,"version":"7.6.1","globals":"9ce4b5f25da6a778f1a3937cc67cb5d9","files":{"main_py":{"hash":"865f34dfa03c79ca8ad1b3bb6adf0a26","index":{"url":"main_py.html","file":"main.py","description":"","nums":{"precision":0,"n_files":1,"n_statements":90,"n_excluded":0,"n_missing":58,"n_branches":0,"n_partial_branches":0,"n_missing_branches":0}}},"test_MainDisplayScoreboard_py":{"hash":"8f3398d539fa055c7571b263506dc5f2","index":{"url":"test_MainDisplayScoreboard_py.html","file":"test_MainDisplayScoreboard.py","description":"","nums":{"precision":0,"n_files":1,"n_statements":29,"n_excluded":0,"n_missing":0,"n_branches":0,"n_partial_branches":0,"n_missing_branches":0}}},"test_MainMain_py":{"hash":"0fffffc81d88b9ce157b165adea5159a","index":{"url":"test_MainMain_py.html","file":"test_MainMain.py","description":"","nums":{"precision":0,"n_files":1,"n_statements":38,"n_excluded":0,"n_missing":24,"n_branches":0,"n_partial_branches":0,"n_missing_branches":0}}},"test_MainPlayGame_py":{"hash":"a6a0647edc2273588adc1c474eb2911d","index":{"url":"test_MainPlayGame_py.html","file":"test_MainPlayGame.py","description":"","nums":{"precision":0,"n_files":1,"n_statements":1,"n_excluded":0,"n_missing":0,"n_branches":0,"n_partial_branches":0,"n_missing_branches":0}}},"test_MainToss_py":{"hash":"d2d908f1c23a035ff54c2f99286ad07f","index":{"url":"test_MainToss_py.html","file":"test_MainToss.py","description":"","nums":{"precision":0,"n_files":1,"n_statements":27,"n_excluded":0,"n_missing":0,"n_branches":0,"n_partial_branches":0,"n_missing_branches":0}}},"test_MainUserTurn_py":{"hash":"6ef82d923cfa0fef9b7656d49a015233","index":{"url":"test_MainUserTurn_py.html","file":"test_MainUserTurn.py","description":"","nums":{"precision":0,"n_files":1,"n_statements":26,"n_excluded":0,"n_missing":22,"n_branches":0,"n_partial_branches":0,"n_missing_branches":0}}},"test_MainWhoWon_py":{"hash":"8addcdb4e1704bf74498fbd52bf1d2b1","index":{"url":"test_MainWhoWon_py.html","file":"test_MainWhoWon.py","description":"","nums":{"precision":0,"n_files":1,"n_statements":36,"n_excluded":0,"n_missing":0,"n_branches":0,"n_partial_branches":0,"n_missing_branches":0}}}}}